capsula/__init__.py
capsula/_backport.py
capsula/_capsule.py
capsula/_cli.py
capsula/_config.py
capsula/_decorator.py
capsula/_encapsulator.py
capsula/_exceptions.py
capsula/_root.py
capsula/_run.py
capsula/_utils.py
capsula/_version.py
capsula/py.typed
capsula/_context/__init__.py
capsula/_context/_base.py
capsula/_context/_command.py
capsula/_context/_cpu.py
capsula/_context/_cwd.py
capsula/_context/_envvar.py
capsula/_context/_file.py
capsula/_context/_function.py
capsula/_context/_git.py
capsula/_context/_platform.py
capsula/_reporter/__init__.py
capsula/_reporter/_base.py
capsula/_reporter/_json.py
capsula/_reporter/_slack.py
capsula/_watcher/__init__.py
capsula/_watcher/_base.py
capsula/_watcher/_exception.py
capsula/_watcher/_time.py
capsula-0.8.0.dist-info/METADATA
capsula-0.8.0.dist-info/WHEEL
capsula-0.8.0.dist-info/entry_points.txt
capsula-0.8.0.dist-info/licenses/LICENSE
capsula-0.8.0.dist-info/RECORD
