Metadata-Version: 2.4
Name: capsula
Version: 0.8.0
Summary: A Python package to capture command/function execution context for reproducibility.
Project-URL: Documentation, https://shunichironomura.github.io/capsula/
Project-URL: Repository, https://github.com/shunichironomura/capsula
Author-email: Shunichiro Nomura <nomura@space.t.u-tokyo.ac.jp>
License: MIT License
License-File: LICENSE
Keywords: cli,reproducibility
Classifier: Development Status :: 4 - Beta
Classifier: Environment :: Console
Classifier: Intended Audience :: Developers
Classifier: Intended Audience :: Education
Classifier: Intended Audience :: Science/Research
Classifier: Programming Language :: Python
Classifier: Programming Language :: Python :: 3 :: Only
Classifier: Programming Language :: Python :: 3.10
Classifier: Programming Language :: Python :: 3.11
Classifier: Programming Language :: Python :: 3.12
Classifier: Programming Language :: Python :: 3.13
Classifier: Programming Language :: Python :: 3.14
Classifier: Topic :: Scientific/Engineering
Requires-Python: >=3.10
Requires-Dist: gitpython>=3.1.41
Requires-Dist: orjson>=3.9.15
Requires-Dist: py-cpuinfo>=9.0.0
Requires-Dist: slack-sdk>=3.33.1
Requires-Dist: tomli>=2.0.1; python_version < '3.11'
Requires-Dist: typer>=0.9.0
Requires-Dist: typing-extensions>=4.7.1; python_version < '3.11'
